pycyber/__init__.py
pycyber/cyber.py
pycyber/cyber_time.py
pycyber/cyber_timer.py
pycyber/parameter.py
pycyber/record.py
pycyber/conf/compute_sched.conf
pycyber/conf/compute_sched_choreography.conf
pycyber/conf/compute_sched_classic.conf
pycyber/conf/control_sched.conf
pycyber/conf/control_sched_choreography.conf
pycyber/conf/control_sched_classic.conf
pycyber/conf/cyber.pb.conf
pycyber/conf/dreamview_sched.conf
pycyber/examples/__init__.py
pycyber/examples/client.py
pycyber/examples/listener.py
pycyber/examples/parameter.py
pycyber/examples/record_channel_info.py
pycyber/examples/record_trans.py
pycyber/examples/service.py
pycyber/examples/talker.py
pycyber/examples/time.py
pycyber/examples/timer.py
pycyber/examples/proto/__init__.py
pycyber/examples/proto/examples_pb2.py
pycyber/internal/_cyber_parameter_wrapper.so
pycyber/internal/_cyber_record_wrapper.so
pycyber/internal/_cyber_time_wrapper.so
pycyber/internal/_cyber_timer_wrapper.so
pycyber/internal/_cyber_wrapper.so
pycyber/internal/fastrtps/libfastcdr.so.1
pycyber/internal/fastrtps/libfastrtps.so.1
pycyber/tools/cyber_channel/cyber_channel.py
pycyber/tools/cyber_launch/cyber_launch.py
pycyber/tools/cyber_node/cyber_node.py
pycyber/tools/cyber_service/cyber_service.py
pycyber-0.0.6.dist-info/LICENSE
pycyber-0.0.6.dist-info/METADATA
pycyber-0.0.6.dist-info/WHEEL
pycyber-0.0.6.dist-info/entry_points.txt
pycyber-0.0.6.dist-info/top_level.txt
pycyber-0.0.6.dist-info/RECORD
