Metadata-Version: 2.1
Name: pycyber
Version: 0.0.6
Summary: Apollo autopilot middleware.
Home-page: https://github.com/daohu527/pycyber
Author: daohu527
Author-email: daohu527@gmail.com
License: UNKNOWN
Project-URL: Bug Tracker, https://github.com/daohu527/pycyber/issues
Platform: UNKNOWN
Classifier: Programming Language :: Python :: 3
Classifier: License :: OSI Approved :: Apache Software License
Classifier: Operating System :: OS Independent
Requires-Python: >=3.6
Requires-Dist: protobuf (>=3.17.0)
